Workbook

Sheet Sheet1
B1: Name of the Fund
B2: UTI Nifty 50 Index Growth Direct Plan
B3: Parag Parikh Flexi Cap Growth Direct Plan
B4: Axis Corporate Bond Growth Direct Plan
B5: ICICI Prudential Equity & Debt Growth Direct Plan
B6: ICICI Prudential Short Term Growth Direct Plan
B7: UTI Nifty Next 50 Index Growth Direct Plan
B8: Nippon India Nifty Smallcap 250 Index Growth Direct Plan
B9: Motilal Oswal Nifty Midcap 150 Index Growth Direct Plan
B10: HDFC Balanced Advantage Growth Direct Plan
B11: SBI Medium To Long Duration Growth Direct Plan
B12: HDFC Small Cap Growth Direct Plan
... B94: HDFC Balanced Growth Plan

Sheet txns
A1: Date | B1: Folio Number | C1: AMFI code | D1: ISIN code | E1: Name of the Fund | F1: Order | G1: Units | H1: NAV | I1: Current Nav | J1: Amount (INR)
A2: 2026-02-11 | B2: 577383970916 | C2: =_xlfn.XLOOKUP(E2,Sheet8!A:A,Sheet8!D:D,"NA") -> 120716 | D2: =_xlfn.XLOOKUP(E2,Sheet8!A:A,Sheet8!E:E,"NA") -> INF789F01XA0 | E2: UTI Nifty 50 Index Growth Direct Plan | F2: buy | G2: 55.108 | H2: 181.4539 | I2: 178.7925 | J2: 9999.5
A3: 2026-02-11 | B3: 18542903 | C3: =_xlfn.XLOOKUP(E3,Sheet8!A:A,Sheet8!D:D,"NA") -> 122639 | D3: =_xlfn.XLOOKUP(E3,Sheet8!A:A,Sheet8!E:E,"NA") -> INF879O01027 | E3: Parag Parikh Flexi Cap Growth Direct Plan | F3: buy | G3: 53.301 | H3: 93.8017 | I3: 92.9299 | J3: 4999.75
A4: 2026-02-11 | B4: 91081817545 | C4: =_xlfn.XLOOKUP(E4,Sheet8!A:A,Sheet8!D:D,"NA") -> 141588 | D4: =_xlfn.XLOOKUP(E4,Sheet8!A:A,Sheet8!E:E,"NA") -> INF846K01ZM8 | E4: Axis Corporate Bond Growth Direct Plan | F4: buy | G4: 267.119 | H4: 18.7173 | I4: 18.7785 | J4: 4999.75
A5: 2026-02-11 | B5: 41440972/44 | C5: =_xlfn.XLOOKUP(E5,Sheet8!A:A,Sheet8!D:D,"NA") -> 120251 | D5: =_xlfn.XLOOKUP(E5,Sheet8!A:A,Sheet8!E:E,"NA") -> INF109K01Y07 | E5: ICICI Prudential Equity & Debt Growth Direct Plan | F5: buy | G5: 16.283 | H5: 460.59 | I5: 455.44 | J5: 7499.63
A6: 2026-02-11 | B6: 41440972/44 | C6: =_xlfn.XLOOKUP(E6,Sheet8!A:A,Sheet8!D:D,"NA") -> 120754 | D6: =_xlfn.XLOOKUP(E6,Sheet8!A:A,Sheet8!E:E,"NA") -> INF109K013N3 | E6: ICICI Prudential Short Term Growth Direct Plan | F6: buy | G6: 43.97 | H6: 68.2245 | I6: 68.3894 | J6: 2999.85
A7: 2026-01-12 | B7: 577383970916 | C7: =_xlfn.XLOOKUP(E7,Sheet8!A:A,Sheet8!D:D,"NA") -> 120716 | D7: =_xlfn.XLOOKUP(E7,Sheet8!A:A,Sheet8!E:E,"NA") -> INF789F01XA0 | E7: UTI Nifty 50 Index Growth Direct Plan | F7: buy | G7: 55.502 | H7: 180.1659 | I7: 178.7925 | J7: 9999.5
A8: 2026-01-12 | B8: 18542903 | C8: =_xlfn.XLOOKUP(E8,Sheet8!A:A,Sheet8!D:D,"NA") -> 122639 | D8: =_xlfn.XLOOKUP(E8,Sheet8!A:A,Sheet8!E:E,"NA") -> INF879O01027 | E8: Parag Parikh Flexi Cap Growth Direct Plan | F8: buy | G8: 53.003 | H8: 94.329 | I8: 92.9299 | J8: 4999.75
A9: 2026-01-12 | B9: 41440972/44 | C9: =_xlfn.XLOOKUP(E9,Sheet8!A:A,Sheet8!D:D,"NA") -> 120754 | D9: =_xlfn.XLOOKUP(E9,Sheet8!A:A,Sheet8!E:E,"NA") -> INF109K013N3 | E9: ICICI Prudential Short Term Growth Direct Plan | F9: buy | G9: 44.113 | H9: 68.0034 | I9: 68.3894 | J9: 2999.85
A10: 2026-01-12 | B10: 41440972/44 | C10: =_xlfn.XLOOKUP(E10,Sheet8!A:A,Sheet8!D:D,"NA") -> 120251 | D10: =_xlfn.XLOOKUP(E10,Sheet8!A:A,Sheet8!E:E,"NA") -> INF109K01Y07 | E10: ICICI Prudential Equity & Debt Growth Direct Plan | F10: buy | G10: 16.514 | H10: 454.14 | I10: 455.44 | J10: 7499.63
A11: 2026-01-12 | B11: 91081817545 | C11: =_xlfn.XLOOKUP(E11,Sheet8!A:A,Sheet8!D:D,"NA") -> 141588 | D11: =_xlfn.XLOOKUP(E11,Sheet8!A:A,Sheet8!E:E,"NA") -> INF846K01ZM8 | E11: Axis Corporate Bond Growth Direct Plan | F11: buy | G11: 267.716 | H11: 18.6756 | I11: 18.7785 | J11: 4999.75
A12: 2025-12-11 | B12: 577383970207 | C12: =_xlfn.XLOOKUP(E12,Sheet8!A:A,Sheet8!D:D,"NA") -> 143341 | D12: =_xlfn.XLOOKUP(E12,Sheet8!A:A,Sheet8!E:E,"NA") -> INF789FC12T1 | E12: UTI Nifty Next 50 Index Growth Direct Plan | F12: buy | G12: 199.07 | H12: 25.1155 | I12: 25.6899 | J12: 4999.75
A13: 2025-12-11 | B13: 577383970916 | C13: =_xlfn.XLOOKUP(E13,Sheet8!A:A,Sheet8!D:D,"NA") -> 120716 | D13: =_xlfn.XLOOKUP(E13,Sheet8!A:A,Sheet8!E:E,"NA") -> INF789F01XA0 | E13: UTI Nifty 50 Index Growth Direct Plan | F13: buy | G13: 55.258 | H13: 180.9594 | I13: 178.7925 | J13: 9999.5
A14: 2025-12-11 | B14: 18542903 | C14: =_xlfn.XLOOKUP(E14,Sheet8!A:A,Sheet8!D:D,"NA") -> 122639 | D14: =_xlfn.XLOOKUP(E14,Sheet8!A:A,Sheet8!E:E,"NA") -> INF879O01027 | E14: Parag Parikh Flexi Cap Growth Direct Plan | F14: buy | G14: 52.776 | H14: 94.735 | I14: 92.9299 | J14: 4999.75
A15: 2025-12-11 | B15: 488218776753 | C15: =_xlfn.XLOOKUP(E15,Sheet8!A:A,Sheet8!D:D,"NA") -> 148519 | D15: =_xlfn.XLOOKUP(E15,Sheet8!A:A,Sheet8!E:E,"NA") -> INF204KB15W0 | E15: Nippon India Nifty Smallcap 250 Index Growth Direct Plan | F15: buy | G15: 124.175 | H15: 32.2109 | I15: 31.6237 | J15: 3999.8
A16: 2025-12-11 | B16: 91012748842 | C16: =_xlfn.XLOOKUP(E16,Sheet8!A:A,Sheet8!D:D,"NA") -> 147622 | D16: =_xlfn.XLOOKUP(E16,Sheet8!A:A,Sheet8!E:E,"NA") -> INF247L01916 | E16: Motilal Oswal Nifty Midcap 150 Index Growth Direct Plan | F16: buy | G16: 126.26 | H16: 39.5987 | I16: 39.7003 | J16: 4999.75
A17: 2025-12-11 | B17: 41440972/44 | C17: =_xlfn.XLOOKUP(E17,Sheet8!A:A,Sheet8!D:D,"NA") -> 120754 | D17: =_xlfn.XLOOKUP(E17,Sheet8!A:A,Sheet8!E:E,"NA") -> INF109K013N3 | E17: ICICI Prudential Short Term Growth Direct Plan | F17: buy | G17: 44.281 | H17: 67.745 | I17: 68.3894 | J17: 2999.85
A18: 2025-12-11 | B18: 41440972/44 | C18: =_xlfn.XLOOKUP(E18,Sheet8!A:A,Sheet8!D:D,"NA") -> 120251 | D18: =_xlfn.XLOOKUP(E18,Sheet8!A:A,Sheet8!E:E,"NA") -> INF109K01Y07 | E18: ICICI Prudential Equity & Debt Growth Direct Plan | F18: buy | G18: 16.509 | H18: 454.28 | I18: 455.44 | J18: 7499.63
A19: 2025-12-11 | B19: 10372451/53 | C19: =_xlfn.XLOOKUP(E19,Sheet8!A:A,Sheet8!D:D,"NA") -> 118968 | D19: =_xlfn.XLOOKUP(E19,Sheet8!A:A,Sheet8!E:E,"NA") -> INF179K01WA6 | E19: HDFC Balanced Advantage Growth Direct Plan | F19: buy | G19: 8.711 | H19: 573.959 | I19: 576.21 | J19: 4999.75
A20: 2025-12-11 | B20: 91081817545 | C20: =_xlfn.XLOOKUP(E20,Sheet8!A:A,Sheet8!D:D,"NA") -> 141588 | D20: =_xlfn.XLOOKUP(E20,Sheet8!A:A,Sheet8!E:E,"NA") -> INF846K01ZM8 | E20: Axis Corporate Bond Growth Direct Plan | F20: buy | G20: 268.574 | H20: 18.6159 | I20: 18.7785 | J20: 4999.75
A21: 2025-11-11 | B21: 91081817545 | C21: =_xlfn.XLOOKUP(E21,Sheet8!A:A,Sheet8!D:D,"NA") -> 141588 | D21: =_xlfn.XLOOKUP(E21,Sheet8!A:A,Sheet8!E:E,"NA") -> INF846K01ZM8 | E21: Axis Corporate Bond Growth Direct Plan | F21: buy | G21: 268.921 | H21: 18.5919 | I21: 18.7785 | J21: 4999.75
A22: 2025-11-11 | B22: 577383970207 | C22: =_xlfn.XLOOKUP(E22,Sheet8!A:A,Sheet8!D:D,"NA") -> 143341 | D22: =_xlfn.XLOOKUP(E22,Sheet8!A:A,Sheet8!E:E,"NA") -> INF789FC12T1 | E22: UTI Nifty Next 50 Index Growth Direct Plan | F22: buy | G22: 193.994 | H22: 25.7727 | I22: 25.6899 | J22: 4999.75
A23: 2025-11-11 | B23: 577383970916 | C23: =_xlfn.XLOOKUP(E23,Sheet8!A:A,Sheet8!D:D,"NA") -> 120716 | D23: =_xlfn.XLOOKUP(E23,Sheet8!A:A,Sheet8!E:E,"NA") -> INF789F01XA0 | E23: UTI Nifty 50 Index Growth Direct Plan | F23: buy | G23: 55.696 | H23: 179.5365 | I23: 178.7925 | J23: 9999.5
A24: 2025-11-11 | B24: 18542903 | C24: =_xlfn.XLOOKUP(E24,Sheet8!A:A,Sheet8!D:D,"NA") -> 122639 | D24: =_xlfn.XLOOKUP(E24,Sheet8!A:A,Sheet8!E:E,"NA") -> INF879O01027 | E24: Parag Parikh Flexi Cap Growth Direct Plan | F24: buy | G24: 53.087 | H24: 94.1798 | I24: 92.9299 | J24: 4999.75
A25: 2025-11-11 | B25: 488218776753 | C25: =_xlfn.XLOOKUP(E25,Sheet8!A:A,Sheet8!D:D,"NA") -> 148519 | D25: =_xlfn.XLOOKUP(E25,Sheet8!A:A,Sheet8!E:E,"NA") -> INF204KB15W0 | E25: Nippon India Nifty Smallcap 250 Index Growth Direct Plan | F25: buy | G25: 118.844 | H25: 33.6559 | I25: 31.6237 | J25: 3999.8
A26: 2025-11-11 | B26: 91012748842 | C26: =_xlfn.XLOOKUP(E26,Sheet8!A:A,Sheet8!D:D,"NA") -> 147622 | D26: =_xlfn.XLOOKUP(E26,Sheet8!A:A,Sheet8!E:E,"NA") -> INF247L01916 | E26: Motilal Oswal Nifty Midcap 150 Index Growth Direct Plan | F26: buy | G26: 124.42 | H26: 40.1843 | I26: 39.7003 | J26: 4999.75
A27: 2025-11-11 | B27: 41440972/44 | C27: =_xlfn.XLOOKUP(E27,Sheet8!A:A,Sheet8!D:D,"NA") -> 120754 | D27: =_xlfn.XLOOKUP(E27,Sheet8!A:A,Sheet8!E:E,"NA") -> INF109K013N3 | E27: ICICI Prudential Short Term Growth Direct Plan | F27: buy | G27: 44.417 | H27: 67.538 | I27: 68.3894 | J27: 2999.85
A28: 2025-11-11 | B28: 41440972/44 | C28: =_xlfn.XLOOKUP(E28,Sheet8!A:A,Sheet8!D:D,"NA") -> 120251 | D28: =_xlfn.XLOOKUP(E28,Sheet8!A:A,Sheet8!E:E,"NA") -> INF109K01Y07 | E28: ICICI Prudential Equity & Debt Growth Direct Plan | F28: buy | G28: 16.581 | H28: 452.31 | I28: 455.44 | J28: 7499.63
A29: 2025-11-11 | B29: 10372451/53 | C29: =_xlfn.XLOOKUP(E29,Sheet8!A:A,Sheet8!D:D,"NA") -> 118968 | D29: =_xlfn.XLOOKUP(E29,Sheet8!A:A,Sheet8!E:E,"NA") -> INF179K01WA6 | E29: HDFC Balanced Advantage Growth Direct Plan | F29: buy | G29: 8.687 | H29: 575.546 | I29: 576.21 | J29: 4999.75
A30: 2025-11-03 | B30: 28647750 | C30: =_xlfn.XLOOKUP(E30,Sheet8!A:A,Sheet8!D:D,"NA") -> 119713 | D30: =_xlfn.XLOOKUP(E30,Sheet8!A:A,Sheet8!E:E,"NA") -> INF200K01SP6 | E30: SBI Medium To Long Duration Growth Direct Plan | F30: buy | G30: 64.679 | H30: 77.3008 | I30: 77.9586 | J30: 4999.75
A31: 2025-10-13 | B31: 11104373/76 | C31: =_xlfn.XLOOKUP(E31,Sheet8!A:A,Sheet8!D:D,"NA") -> 130503 | D31: =_xlfn.XLOOKUP(E31,Sheet8!A:A,Sheet8!E:E,"NA") -> INF179KA1RW5 | E31: HDFC Small Cap Growth Direct Plan | F31: buy | G31: 1549.157 | H31: 161.37 | I31: 153.431 | J31: 249987.5
A32: 2025-10-13 | B32: 24222120 | C32: =_xlfn.XLOOKUP(E32,Sheet8!A:A,Sheet8!D:D,"NA") -> 149134 | D32: =_xlfn.XLOOKUP(E32,Sheet8!A:A,Sheet8!E:E,"NA") -> INF200KA1Y73 | E32: SBI Balanced Advantage Growth Direct Plan | F32: buy | G32: 24758.592 | H32: 16.1552 | I32: 16.7701 | J32: 399980
A33: 2025-10-13 | B33: 91062128393 | C33: =_xlfn.XLOOKUP(E33,Sheet8!A:A,Sheet8!D:D,"NA") -> 141588 | D33: =_xlfn.XLOOKUP(E33,Sheet8!A:A,Sheet8!E:E,"NA") -> INF846K01ZM8 | E33: Axis Corporate Bond Growth Direct Plan | F33: buy | G33: 81662.565 | H33: 18.4898 | I33: 18.7785 | J33: 1509924.5
A34: 2025-10-13 | B34: 91062128393 | C34: =_xlfn.XLOOKUP(E34,Sheet8!A:A,Sheet8!D:D,"NA") -> 149466 | D34: =_xlfn.XLOOKUP(E34,Sheet8!A:A,Sheet8!E:E,"NA") -> INF846K019E7 | E34: Axis Nifty Next 50 Index Growth Direct Plan | F34: buy | G34: 36643.36 | H34: 16.919 | I34: 17.1709 | J34: 619969
A35: 2025-10-13 | B35: 599295234843 | C35: =_xlfn.XLOOKUP(E35,Sheet8!A:A,Sheet8!D:D,"NA") -> 120716 | D35: =_xlfn.XLOOKUP(E35,Sheet8!A:A,Sheet8!E:E,"NA") -> INF789F01XA0 | E35: UTI Nifty 50 Index Growth Direct Plan | F35: buy | G35: 11360.951 | H35: 176.0328 | I35: 178.7925 | J35: 1999900
A36: 2025-10-13 | B36: 8841618/87 | C36: =_xlfn.XLOOKUP(E36,Sheet8!A:A,Sheet8!D:D,"NA") -> 120616 | D36: =_xlfn.XLOOKUP(E36,Sheet8!A:A,Sheet8!E:E,"NA") -> INF109K01S39 | E36: ICICI Prudential Regular Saving Growth Direct Plan | F36: buy | G36: 3529.742 | H36: 84.9878 | I36: 86.0312 | J36: 299985
A37: 2025-10-13 | B37: 11104373/76 | C37: =_xlfn.XLOOKUP(E37,Sheet8!A:A,Sheet8!D:D,"NA") -> 118955 | D37: =_xlfn.XLOOKUP(E37,Sheet8!A:A,Sheet8!E:E,"NA") -> INF179K01UT0 | E37: HDFC Flexicap Growth Direct Plan | F37: buy | G37: 80.308 | H37: 2241.258 | I37: 2282.94 | J37: 179991
A38: 2025-10-13 | B38: 11104373/76 | C38: =_xlfn.XLOOKUP(E38,Sheet8!A:A,Sheet8!D:D,"NA") -> 118950 | D38: =_xlfn.XLOOKUP(E38,Sheet8!A:A,Sheet8!E:E,"NA") -> INF179K01VK7 | E38: HDFC Focused Growth Direct Plan | F38: buy | G38: 372.231 | H38: 268.637 | I38: 274.182 | J38: 99995
A39: 2025-10-07 | B39: 13993567/26 | C39: =_xlfn.XLOOKUP(E39,Sheet8!A:A,Sheet8!D:D,"NA") -> 146010 | D39: =_xlfn.XLOOKUP(E39,Sheet8!A:A,Sheet8!E:E,"NA") -> INF277K013S8 | E39: Tata Balanced Advantage Growth Direct Plan | F39: buy | G39: 14697.598 | H39: 22.7917 | I39: 23.3771 | J39: 334983.25
A40: 2025-10-07 | B40: 3556322/64 | C40: =_xlfn.XLOOKUP(E40,Sheet8!A:A,Sheet8!D:D,"NA") -> 146010 | D40: =_xlfn.XLOOKUP(E40,Sheet8!A:A,Sheet8!E:E,"NA") -> INF277K013S8 | E40: Tata Balanced Advantage Growth Direct Plan | F40: buy | G40: 14697.598 | H40: 22.7917 | I40: 23.3771 | J40: 334983.25
A41: 2025-10-06 | B41: 599304584441 | C41: =_xlfn.XLOOKUP(E41,Sheet8!A:A,Sheet8!D:D,"NA") -> 120663 | D41: =_xlfn.XLOOKUP(E41,Sheet8!A:A,Sheet8!E:E,"NA") -> INF789F01TA8 | E41: UTI Flexi Cap Growth Direct Plan | F41: buy | G41: 14.234 | H41: 351.2613 | I41: 328.8686 | J41: 4999.75
A42: 2025-10-06 | B42: 7993233136 | C42: =_xlfn.XLOOKUP(E42,Sheet8!A:A,Sheet8!D:D,"NA") -> 118834 | D42: =_xlfn.XLOOKUP(E42,Sheet8!A:A,Sheet8!E:E,"NA") -> INF769K01BI1 | E42: Mirae Asset Large & Midcap Growth Direct Plan | F42: buy | G42: 29.159 | H42: 171.467 | I42: 175.2 | J42: 4999.75
A43: 2025-10-06 | B43: 18265571 | C43: =_xlfn.XLOOKUP(E43,Sheet8!A:A,Sheet8!D:D,"NA") -> 122639 | D43: =_xlfn.XLOOKUP(E43,Sheet8!A:A,Sheet8!E:E,"NA") -> INF879O01027 | E43: Parag Parikh Flexi Cap Growth Direct Plan | F43: buy | G43: 7203.383 | H43: 93.0072 | I43: 92.9299 | J43: 669966.5
A44: 2025-10-03 | B44: 91062128393 | C44: =_xlfn.XLOOKUP(E44,Sheet8!A:A,Sheet8!D:D,"NA") -> 120466 | D44: =_xlfn.XLOOKUP(E44,Sheet8!A:A,Sheet8!E:E,"NA") -> INF846K01DN3 | E44: Axis Large Cap Growth Direct Plan | F44: buy | G44: 71.558 | H44: 69.87 | I44: 70.9 | J44: 4999.75
A45: 2025-10-03 | B45: 8841618/87 | C45: =_xlfn.XLOOKUP(E45,Sheet8!A:A,Sheet8!D:D,"NA") -> 120377 | D45: =_xlfn.XLOOKUP(E45,Sheet8!A:A,Sheet8!E:E,"NA") -> INF109K012B0 | E45: ICICI Prudential Balanced Advantage Growth Direct Plan | F45: buy | G45: 119.084 | H45: 83.97 | I45: 86.57 | J45: 9999.5
A46: 2025-10-02 | B46: 8841618/87 | C46: =_xlfn.XLOOKUP(E46,Sheet8!A:A,Sheet8!D:D,"NA") -> 120197 | D46: =_xlfn.XLOOKUP(E46,Sheet8!A:A,Sheet8!E:E,"NA") -> INF109K01Q49 | E46: ICICI Prudential Liquid Growth Direct Plan | F46: buy | G46: 12.622 | H46: 396.1211 | I46: 405.2741 | J46: 4999.75
A47: 2025-10-01 | B47: 28647750 | C47: =_xlfn.XLOOKUP(E47,Sheet8!A:A,Sheet8!D:D,"NA") -> 119713 | D47: =_xlfn.XLOOKUP(E47,Sheet8!A:A,Sheet8!E:E,"NA") -> INF200K01SP6 | E47: SBI Medium To Long Duration Growth Direct Plan | F47: buy | G47: 65.019 | H47: 76.8968 | I47: 77.9586 | J47: 4999.75
A48: 2025-09-25 | B48: 15862779/57 | C48: =_xlfn.XLOOKUP(E48,Sheet8!A:A,Sheet8!D:D,"NA") -> 102001 | D48: =_xlfn.XLOOKUP(E48,Sheet8!A:A,Sheet8!E:E,"NA") -> INF179K01BC6 | E48: HDFC Large Cap Regular IDCW Payout Plan | F48: sell | G48: 1800.916 | H48: 57.309 | I48: 53.449 | J48: 103207.67
A49: 2025-09-25 | B49: 15862779/57 | C49: =_xlfn.XLOOKUP(E49,Sheet8!A:A,Sheet8!D:D,"NA") -> 136090 | D49: =_xlfn.XLOOKUP(E49,Sheet8!A:A,Sheet8!E:E,"NA") -> INF179KB1MG8 | E49: HDFC Retirement Saving Equity Regular Growth Plan | F49: sell | G49: 1970.055 | H49: 50.551 | I49: 50.852 | J49: 99587.25
A50: 2025-09-23 | B50: 10825996/37 | C50: =_xlfn.XLOOKUP(E50,Sheet8!A:A,Sheet8!D:D,"NA") -> 102948 | D50: =_xlfn.XLOOKUP(E50,Sheet8!A:A,Sheet8!E:E,"NA") -> INF179K01AS4 | E50: HDFC Hybrid Equity Regular Growth Plan | F50: sell | G50: 209.562 | H50: 117.568 | I50: 118.614 | J50: 24637.67
A51: 2025-09-23 | B51: 10825996/37 | C51: =_xlfn.XLOOKUP(E51,Sheet8!A:A,Sheet8!D:D,"NA") -> 102948 | D51: =_xlfn.XLOOKUP(E51,Sheet8!A:A,Sheet8!E:E,"NA") -> INF179K01AS4 | E51: HDFC Hybrid Equity Regular Growth Plan | F51: sell | G51: 3193.191 | H51: 118.756 | I51: 118.614 | J51: 379206.64
A52: 2025-09-23 | B52: 10853606/45 | C52: =_xlfn.XLOOKUP(E52,Sheet8!A:A,Sheet8!D:D,"NA") -> 102147 | D52: =_xlfn.XLOOKUP(E52,Sheet8!A:A,Sheet8!E:E,"NA") -> INF179K01AE4 | E52: HDFC Hybrid Debt Growth Plan | F52: sell | G52: 634.345 | H52: 82.2149 | I52: 83.6798 | J52: 52152.6
A53: 2025-09-23 | B53: 10927499/11 | C53: =_xlfn.XLOOKUP(E53,Sheet8!A:A,Sheet8!D:D,"NA") -> 113048 | D53: =_xlfn.XLOOKUP(E53,Sheet8!A:A,Sheet8!E:E,"NA") -> INF179K01CV4 | E53: HDFC Short Term Debt Regular Growth Plan | F53: sell | G53: 4931.768 | H53: 32.4872 | I53: 33.2155 | J53: 160219.32
A54: 2025-09-23 | B54: 3900867/61 | C54: =_xlfn.XLOOKUP(E54,Sheet8!A:A,Sheet8!D:D,"NA") -> 112090 | D54: =_xlfn.XLOOKUP(E54,Sheet8!A:A,Sheet8!E:E,"NA") -> INF174K01336 | E54: Kotak Flexicap Growth Plan | F54: sell | G54: 3149.958 | H54: 85.65 | I54: 87.925 | J54: 269791.18
A55: 2025-09-23 | B55: 3900867/61 | C55: =_xlfn.XLOOKUP(E55,Sheet8!A:A,Sheet8!D:D,"NA") -> 112090 | D55: =_xlfn.XLOOKUP(E55,Sheet8!A:A,Sheet8!E:E,"NA") -> INF174K01336 | E55: Kotak Flexicap Growth Plan | F55: sell | G55: 787.166 | H55: 85.65 | I55: 87.925 | J55: 67420.07
A56: 2025-09-23 | B56: 3900867/61 | C56: =_xlfn.XLOOKUP(E56,Sheet8!A:A,Sheet8!D:D,"NA") -> 104908 | D56: =_xlfn.XLOOKUP(E56,Sheet8!A:A,Sheet8!E:E,"NA") -> INF174K01DS9 | E56: Kotak Midcap Growth Plan | F56: sell | G56: 1528.255 | H56: 138.903 | I56: 136.203 | J56: 212277.09
A57: 2025-09-23 | B57: 14956452 | C57: =_xlfn.XLOOKUP(E57,Sheet8!A:A,Sheet8!D:D,"NA") -> 102205 | D57: =_xlfn.XLOOKUP(E57,Sheet8!A:A,Sheet8!E:E,"NA") -> INF200K01958 | E57: SBI Dynamic Bond Growth Plan | F57: sell | G57: 964.994 | H57: 35.9529 | I57: 36.4126 | J57: 34694.33
A58: 2025-09-23 | B58: 14956452 | C58: =_xlfn.XLOOKUP(E58,Sheet8!A:A,Sheet8!D:D,"NA") -> 102756 | D58: =_xlfn.XLOOKUP(E58,Sheet8!A:A,Sheet8!E:E,"NA") -> INF200K01370 | E58: SBI Focused Regular Growth Plan | F58: sell | G58: 738.613 | H58: 361.9417 | I58: 375.5735 | J58: 267332.17
A59: 2025-09-23 | B59: 14956452 | C59: =_xlfn.XLOOKUP(E59,Sheet8!A:A,Sheet8!D:D,"NA") -> 103616 | D59: =_xlfn.XLOOKUP(E59,Sheet8!A:A,Sheet8!E:E,"NA") -> INF200K01164 | E59: SBI Large Cap Growth Plan | F59: sell | G59: 736.217 | H59: 93.2495 | I59: 95.4299 | J59: 68651.18
A60: 2025-09-23 | B60: 14956452 | C60: =_xlfn.XLOOKUP(E60,Sheet8!A:A,Sheet8!D:D,"NA") -> 103616 | D60: =_xlfn.XLOOKUP(E60,Sheet8!A:A,Sheet8!E:E,"NA") -> INF200K01164 | E60: SBI Large Cap Growth Plan | F60: sell | G60: 26.296 | H60: 93.2495 | I60: 95.4299 | J60: 2452.07
A61: 2025-09-23 | B61: 14956452 | C61: =_xlfn.XLOOKUP(E61,Sheet8!A:A,Sheet8!D:D,"NA") -> 102941 | D61: =_xlfn.XLOOKUP(E61,Sheet8!A:A,Sheet8!E:E,"NA") -> INF200K01560 | E61: SBI Midcap Growth Plan | F61: sell | G61: 434.867 | H61: 231.0637 | I61: 234.4604 | J61: 100480.92
A62: 2025-09-23 | B62: 14956452 | C62: =_xlfn.XLOOKUP(E62,Sheet8!A:A,Sheet8!D:D,"NA") -> 102941 | D62: =_xlfn.XLOOKUP(E62,Sheet8!A:A,Sheet8!E:E,"NA") -> INF200K01560 | E62: SBI Midcap Growth Plan | F62: sell | G62: 52.496 | H62: 228.7531 | I62: 234.4604 | J62: 12008.51
A63: 2025-09-23 | B63: 1017644260 | C63: =_xlfn.XLOOKUP(E63,Sheet8!A:A,Sheet8!D:D,"NA") -> NA | D63: =_xlfn.XLOOKUP(E63,Sheet8!A:A,Sheet8!E:E,"NA") -> NA | E63: Aditya Birla Sun Life Corporate Bond Regular Growth Plan | F63: sell | G63: 4635.196 | H63: 114.2012 | I63: 116.4035 | J63: 529344.95
A64: 2025-09-23 | B64: 1017644260 | C64: =_xlfn.XLOOKUP(E64,Sheet8!A:A,Sheet8!D:D,"NA") -> 122644 | D64: =_xlfn.XLOOKUP(E64,Sheet8!A:A,Sheet8!E:E,"NA") -> INF209K01MG9 | E64: Aditya Birla Sun Life Floating Rate Regular Growth Plan | F64: sell | G64: 401.166 | H64: 353.3315 | I64: 361.8035 | J64: 141744.58
A65: 2025-09-23 | B65: 1017644260 | C65: =_xlfn.XLOOKUP(E65,Sheet8!A:A,Sheet8!D:D,"NA") -> 122644 | D65: =_xlfn.XLOOKUP(E65,Sheet8!A:A,Sheet8!E:E,"NA") -> INF209K01MG9 | E65: Aditya Birla Sun Life Floating Rate Regular Growth Plan | F65: sell | G65: 401.166 | H65: 353.3315 | I65: 361.8035 | J65: 141744.58
A66: 2025-09-23 | B66: 1017828684 | C66: =_xlfn.XLOOKUP(E66,Sheet8!A:A,Sheet8!D:D,"NA") -> 102767 | D66: =_xlfn.XLOOKUP(E66,Sheet8!A:A,Sheet8!E:E,"NA") -> INF209K01793 | E66: Aditya Birla Sun Life Dynamic Bond Retail Growth Plan | F66: sell | G66: 293.161 | H66: 46.7035 | I66: 47.5598 | J66: 13691.65
A67: 2025-09-23 | B67: 1017828684 | C67: =_xlfn.XLOOKUP(E67,Sheet8!A:A,Sheet8!D:D,"NA") -> 101843 | D67: =_xlfn.XLOOKUP(E67,Sheet8!A:A,Sheet8!E:E,"NA") -> INF209K01975 | E67: Aditya Birla Sun Life Short Term Growth Plan | F67: sell | G67: 804.12 | H67: 48.2319 | I67: 49.3189 | J67: 38784.23
A68: 2025-09-23 | B68: 1038758180 | C68: =_xlfn.XLOOKUP(E68,Sheet8!A:A,Sheet8!D:D,"NA") -> NA | D68: =_xlfn.XLOOKUP(E68,Sheet8!A:A,Sheet8!E:E,"NA") -> NA | E68: Aditya Birla Sun Life Corporate Bond Regular Growth Plan | F68: sell | G68: 861.577 | H68: 114.2012 | I68: 116.4035 | J68: 98393.15
A69: 2025-09-23 | B69: 5254039/92 | C69: =_xlfn.XLOOKUP(E69,Sheet8!A:A,Sheet8!D:D,"NA") -> 101837 | D69: =_xlfn.XLOOKUP(E69,Sheet8!A:A,Sheet8!E:E,"NA") -> INF740K01599 | E69: DSP Credit Risk Regular Growth Plan | F69: sell | G69: 1130.556 | H69: 50.1539 | I69: 50.3151 | J69: 56701.79
A70: 2025-09-23 | B70: 5428922/19 | C70: =_xlfn.XLOOKUP(E70,Sheet8!A:A,Sheet8!D:D,"NA") -> 103820 | D70: =_xlfn.XLOOKUP(E70,Sheet8!A:A,Sheet8!E:E,"NA") -> INF740K01078 | E70: DSP Large & Mid Cap Regular Growth Plan | F70: sell | G70: 232.36 | H70: 619.944 | I70: 637.382 | J70: 144048.75
A71: 2025-09-23 | B71: 19773349 | C71: =_xlfn.XLOOKUP(E71,Sheet8!A:A,Sheet8!D:D,"NA") -> 100473 | D71: =_xlfn.XLOOKUP(E71,Sheet8!A:A,Sheet8!E:E,"NA") -> INF090I01809 | E71: Franklin India Mid Cap Growth Plan | F71: sell | G71: 130.329 | H71: 2756.0257 | I71: 2732.9847 | J71: 359186.47
A72: 2025-09-23 | B72: 19773349 | C72: =_xlfn.XLOOKUP(E72,Sheet8!A:A,Sheet8!D:D,"NA") -> 100473 | D72: =_xlfn.XLOOKUP(E72,Sheet8!A:A,Sheet8!E:E,"NA") -> INF090I01809 | E72: Franklin India Mid Cap Growth Plan | F72: sell | G72: 49.234 | H72: 2756.0257 | I72: 2732.9847 | J72: 135688.85
A73: 2025-09-23 | B73: 19773349 | C73: =_xlfn.XLOOKUP(E73,Sheet8!A:A,Sheet8!D:D,"NA") -> 100473 | D73: =_xlfn.XLOOKUP(E73,Sheet8!A:A,Sheet8!E:E,"NA") -> INF090I01809 | E73: Franklin India Mid Cap Growth Plan | F73: sell | G73: 13.561 | H73: 2728.4654 | I73: 2732.9847 | J73: 37000.33
A74: 2025-09-23 | B74: 7976487/51 | C74: =_xlfn.XLOOKUP(E74,Sheet8!A:A,Sheet8!D:D,"NA") -> 108466 | D74: =_xlfn.XLOOKUP(E74,Sheet8!A:A,Sheet8!E:E,"NA") -> INF109K01BL4 | E74: ICICI Prudential Large Cap Growth Plan | F74: sell | G74: 25.791 | H74: 110.68 | I74: 113.45 | J74: 2854.52
A75: 2025-09-23 | B75: 8631711/84 | C75: =_xlfn.XLOOKUP(E75,Sheet8!A:A,Sheet8!D:D,"NA") -> 108466 | D75: =_xlfn.XLOOKUP(E75,Sheet8!A:A,Sheet8!E:E,"NA") -> INF109K01BL4 | E75: ICICI Prudential Large Cap Growth Plan | F75: sell | G75: 113.429 | H75: 110.68 | I75: 113.45 | J75: 12554.23
A76: 2025-09-23 | B76: 8631711/84 | C76: =_xlfn.XLOOKUP(E76,Sheet8!A:A,Sheet8!D:D,"NA") -> 108466 | D76: =_xlfn.XLOOKUP(E76,Sheet8!A:A,Sheet8!E:E,"NA") -> INF109K01BL4 | E76: ICICI Prudential Large Cap Growth Plan | F76: sell | G76: 2318.683 | H76: 111.8 | I76: 113.45 | J76: 259226.13
A77: 2025-09-23 | B77: 3556322/64 | C77: =_xlfn.XLOOKUP(E77,Sheet8!A:A,Sheet8!D:D,"NA") -> 100414 | D77: =_xlfn.XLOOKUP(E77,Sheet8!A:A,Sheet8!E:E,"NA") -> INF277K01303 | E77: Tata Aggressive Hybrid Growth Plan | F77: sell | G77: 761.454 | H77: 438.4935 | I77: 444.5697 | J77: 333889.23
A78: 2025-09-23 | B78: 3556322/64 | C78: =_xlfn.XLOOKUP(E78,Sheet8!A:A,Sheet8!D:D,"NA") -> 100414 | D78: =_xlfn.XLOOKUP(E78,Sheet8!A:A,Sheet8!E:E,"NA") -> INF277K01303 | E78: Tata Aggressive Hybrid Growth Plan | F78: sell | G78: 99.24 | H78: 434.1086 | I78: 444.5697 | J78: 43080.58
A79: 2025-09-23 | B79: 91012748842 | C79: =_xlfn.XLOOKUP(E79,Sheet8!A:A,Sheet8!D:D,"NA") -> 129047 | D79: =_xlfn.XLOOKUP(E79,Sheet8!A:A,Sheet8!E:E,"NA") -> INF247L01528 | E79: Motilal Oswal Flexi Cap Regular Growth Plan | F79: sell | G79: 4560.151 | H79: 63.0641 | I79: 57.439 | J79: 287578.94
A80: 2025-09-23 | B80: 7993233136 | C80: =_xlfn.XLOOKUP(E80,Sheet8!A:A,Sheet8!D:D,"NA") -> 107578 | D80: =_xlfn.XLOOKUP(E80,Sheet8!A:A,Sheet8!E:E,"NA") -> INF769K01010 | E80: Mirae Asset Large Cap Regular Growth Plan | F80: sell | G80: 1280.168 | H80: 114.013 | I80: 114.838 | J80: 145953.93
A81: 2025-09-23 | B81: 7995118154 | C81: =_xlfn.XLOOKUP(E81,Sheet8!A:A,Sheet8!D:D,"NA") -> 107578 | D81: =_xlfn.XLOOKUP(E81,Sheet8!A:A,Sheet8!E:E,"NA") -> INF769K01010 | E81: Mirae Asset Large Cap Regular Growth Plan | F81: sell | G81: 997.775 | H81: 114.161 | I81: 114.838 | J81: 113905.85
A82: 2025-09-23 | B82: 79911180851 | C82: =_xlfn.XLOOKUP(E82,Sheet8!A:A,Sheet8!D:D,"NA") -> 107578 | D82: =_xlfn.XLOOKUP(E82,Sheet8!A:A,Sheet8!E:E,"NA") -> INF769K01010 | E82: Mirae Asset Large Cap Regular Growth Plan | F82: sell | G82: 1069.293 | H82: 114.161 | I82: 114.838 | J82: 122070.34
A83: 2025-09-23 | B83: 79911180851 | C83: =_xlfn.XLOOKUP(E83,Sheet8!A:A,Sheet8!D:D,"NA") -> 107578 | D83: =_xlfn.XLOOKUP(E83,Sheet8!A:A,Sheet8!E:E,"NA") -> INF769K01010 | E83: Mirae Asset Large Cap Regular Growth Plan | F83: sell | G83: 2386.705 | H83: 114.161 | I83: 114.838 | J83: 272465.91
A84: 2025-09-23 | B84: 79928272526 | C84: =_xlfn.XLOOKUP(E84,Sheet8!A:A,Sheet8!D:D,"NA") -> 145695 | D84: =_xlfn.XLOOKUP(E84,Sheet8!A:A,Sheet8!E:E,"NA") -> INF769K01EI5 | E84: Mirae Asset Equity Saving Regular Growth Plan | F84: sell | G84: 2573.34 | H84: 20.445 | I84: 21.01 | J84: 52611.41
A85: 2025-09-23 | B85: 91081817545 | C85: =_xlfn.XLOOKUP(E85,Sheet8!A:A,Sheet8!D:D,"NA") -> 120468 | D85: =_xlfn.XLOOKUP(E85,Sheet8!A:A,Sheet8!E:E,"NA") -> INF846K01CQ8 | E85: Axis Focused Regular Growth Plan | F85: sell | G85: 3920.031 | H85: 55.98 | I85: 53.13 | J85: 219441.15
A86: 2025-09-23 | B86: 91081817545 | C86: =_xlfn.XLOOKUP(E86,Sheet8!A:A,Sheet8!D:D,"NA") -> 120468 | D86: =_xlfn.XLOOKUP(E86,Sheet8!A:A,Sheet8!E:E,"NA") -> INF846K01CQ8 | E86: Axis Focused Regular Growth Plan | F86: sell | G86: 6536.805 | H86: 55.98 | I86: 53.13 | J86: 365926.68
A87: 2025-09-23 | B87: 91081817545 | C87: =_xlfn.XLOOKUP(E87,Sheet8!A:A,Sheet8!D:D,"NA") -> 112277 | D87: =_xlfn.XLOOKUP(E87,Sheet8!A:A,Sheet8!E:E,"NA") -> INF846K01164 | E87: Axis Large Cap Regular Growth Plan | F87: sell | G87: 1648.994 | H87: 61.39 | I87: 61.32 | J87: 101230.73
A88: 2025-09-23 | B88: 19773363 | C88: =_xlfn.XLOOKUP(E88,Sheet8!A:A,Sheet8!D:D,"NA") -> 100471 | D88: =_xlfn.XLOOKUP(E88,Sheet8!A:A,Sheet8!E:E,"NA") -> INF090I01171 | E88: Franklin India Large Cap Growth Plan | F88: sell | G88: 149.772 | H88: 1037.6069 | I88: 1038.648 | J88: 155402.9
A89: 2025-09-23 | B89: 22437149 | C89: =_xlfn.XLOOKUP(E89,Sheet8!A:A,Sheet8!D:D,"NA") -> 100473 | D89: =_xlfn.XLOOKUP(E89,Sheet8!A:A,Sheet8!E:E,"NA") -> INF090I01809 | E89: Franklin India Mid Cap Growth Plan | F89: sell | G89: 102.52 | H89: 2756.0257 | I89: 2732.9847 | J89: 282544.93
A90: 2025-09-23 | B90: 1813606/09 | C90: =_xlfn.XLOOKUP(E90,Sheet8!A:A,Sheet8!D:D,"NA") -> 118483 | D90: =_xlfn.XLOOKUP(E90,Sheet8!A:A,Sheet8!E:E,"NA") -> INF194K013A6 | E90: Bandhan Nifty 50 Index Regular IDCW Reinvest Plan | F90: sell | G90: 580.548 | H90: 49.2143 | I90: 49.994 | J90: 28570.97
A91: 2025-09-23 | B91: 10372451/53 | C91: =_xlfn.XLOOKUP(E91,Sheet8!A:A,Sheet8!D:D,"NA") -> 101281 | D91: =_xlfn.XLOOKUP(E91,Sheet8!A:A,Sheet8!E:E,"NA") -> INF179K01LA9 | E91: HDFC BSE Sensex Index Regular Growth Plan | F91: sell | G91: 169.77 | H91: 761.2533 | I91: 768.3617 | J91: 129236.66
A92: 2025-09-23 | B92: 10372451/53 | C92: =_xlfn.XLOOKUP(E92,Sheet8!A:A,Sheet8!D:D,"NA") -> 118987 | D92: =_xlfn.XLOOKUP(E92,Sheet8!A:A,Sheet8!E:E,"NA") -> INF179K01XD8 | E92: HDFC Corporate Bond Growth Plan | F92: sell | G92: 2599.003 | H92: 32.9308 | I92: 33.5303 | J92: 85587.25
A93: 2025-09-23 | B93: 10372451/53 | C93: =_xlfn.XLOOKUP(E93,Sheet8!A:A,Sheet8!D:D,"NA") -> 105758 | D93: =_xlfn.XLOOKUP(E93,Sheet8!A:A,Sheet8!E:E,"NA") -> INF179K01CR2 | E93: HDFC Mid Cap Growth Plan | F93: sell | G93: 616.321 | H93: 195.838 | I93: 202.734 | J93: 120697.9
A94: 2025-09-23 | B94: 10372451/53 | C94: =_xlfn.XLOOKUP(E94,Sheet8!A:A,Sheet8!D:D,"NA") -> 105758 | D94: =_xlfn.XLOOKUP(E94,Sheet8!A:A,Sheet8!E:E,"NA") -> INF179K01CR2 | E94: HDFC Mid Cap Growth Plan | F94: sell | G94: 65.273 | H94: 193.88 | I94: 202.734 | J94: 12654.97
A95: 2025-09-09 | B95: 1038758180 | C95: =_xlfn.XLOOKUP(E95,Sheet8!A:A,Sheet8!D:D,"NA") -> NA | D95: =_xlfn.XLOOKUP(E95,Sheet8!A:A,Sheet8!E:E,"NA") -> NA | E95: Aditya Birla Sun Life Corporate Bond Regular Growth Plan | F95: buy | G95: 8.775 | H95: 113.9598 | I95: 116.4035 | J95: 999.95
A96: 2025-09-09 | B96: 10927499/11 | C96: =_xlfn.XLOOKUP(E96,Sheet8!A:A,Sheet8!D:D,"NA") -> 113048 | D96: =_xlfn.XLOOKUP(E96,Sheet8!A:A,Sheet8!E:E,"NA") -> INF179K01CV4 | E96: HDFC Short Term Debt Regular Growth Plan | F96: buy | G96: 61.711 | H96: 32.4077 | I96: 33.2155 | J96: 1999.9
A97: 2025-09-08 | B97: 10825996/37 | C97: =_xlfn.XLOOKUP(E97,Sheet8!A:A,Sheet8!D:D,"NA") -> 102948 | D97: =_xlfn.XLOOKUP(E97,Sheet8!A:A,Sheet8!E:E,"NA") -> INF179K01AS4 | E97: HDFC Hybrid Equity Regular Growth Plan | F97: buy | G97: 17.073 | H97: 117.135 | I97: 118.614 | J97: 1999.9
A98: 2025-09-08 | B98: 19773349 | C98: =_xlfn.XLOOKUP(E98,Sheet8!A:A,Sheet8!D:D,"NA") -> 100473 | D98: =_xlfn.XLOOKUP(E98,Sheet8!A:A,Sheet8!E:E,"NA") -> INF090I01809 | E98: Franklin India Mid Cap Growth Plan | F98: buy | G98: 1.1 | H98: 2726.7159 | I98: 2732.9847 | J98: 2999.85
A99: 2025-09-08 | B99: 10372451/53 | C99: =_xlfn.XLOOKUP(E99,Sheet8!A:A,Sheet8!D:D,"NA") -> 105758 | D99: =_xlfn.XLOOKUP(E99,Sheet8!A:A,Sheet8!E:E,"NA") -> INF179K01CR2 | E99: HDFC Mid Cap Growth Plan | F99: buy | G99: 5.199 | H99: 192.327 | I99: 202.734 | J99: 999.95
A100: 2025-09-08 | B100: 14956452 | C100: =_xlfn.XLOOKUP(E100,Sheet8!A:A,Sheet8!D:D,"NA") -> 102941 | D100: =_xlfn.XLOOKUP(E100,Sheet8!A:A,Sheet8!E:E,"NA") -> INF200K01560 | E100: SBI Midcap Growth Plan | F100: buy | G100: 4.393 | H100: 227.6456 | I100: 234.4604 | J100: 999.95
...

Sheet Sheet8
A2: Axis Nifty Next 50 Index Growth Direct Plan | B2: 120377 | C2: INF846K01D22 | D2: 149466 | E2: INF846K019E7
A3: SBI Balanced Advantage Growth Direct Plan | B3: 149453 | C3: INF754K01HL9 | D3: 149134 | E3: INF200KA1Y73
A4: ICICI Prudential Regular Saving Growth Direct Plan | B4: 120438 | C4: INF109K01X46 | D4: 120616 | E4: INF109K01S39
A5: UTI Value Growth Direct Plan | B5: 119948 | C5: INF209K01V26 | D5: 120751 | E5: INF789F01VB2
A6: HDFC Corporate Bond Growth Direct Plan | B6: 120046 | C6: INF179K01XY2 | D6: 118987 | E6: INF179K01XD8
A7: SBI Focused Growth Direct Plan | B7: 120516 | C7: INF754K01629 | D7: 119727 | E7: INF200K01RJ1
A8: Motilal Oswal Nifty Midcap 150 Index Growth Direct Plan | B8: 147113 | C8: INF247L01AF9 | D8: 147622 | E8: INF247L01916
A9: Canara Robeco Large Cap Growth Direct Plan | B9: 120586 | C9: INF209K01YY7 | D9: 118269 | E9: INF760K01FR2
A10: Axis Focused Growth Direct Plan | D10: 120468 | E10: INF846K01CQ8
A11: ICICI Prudential Short Term Growth Direct Plan | D11: 120754 | E11: INF109K013N3
A12: Canara Robeco Flexi Cap Growth Direct Plan | D12: 118275 | E12: INF760K01EF0
A13: Aditya Birla Sun Life Dynamic Bond Retail Growth Plan | D13: 102767 | E13: INF209K01793
A14: Aditya Birla Sun Life Floating Rate Regular Growth Plan | D14: 122644 | E14: INF209K01MG9
A15: Aditya Birla Sun Life Large Cap Growth Plan | D15: 103174 | E15: INF209K01BR9
A16: Aditya Birla Sun Life Short Term Growth Plan | D16: 101843 | E16: INF209K01975
A17: Axis Corporate Bond Growth Direct Plan | D17: 141588 | E17: INF846K01ZM8
A18: Axis Dynamic Bond Growth Direct Plan | D18: 115068 | E18: INF846K01917
A19: Axis Focused Regular Growth Plan | D19: 120468 | E19: INF846K01CQ8
A20: Axis Large Cap Growth Direct Plan | D20: 120466 | E20: INF846K01DN3
A21: Axis Large Cap Regular Growth Plan | D21: 112277 | E21: INF846K01164
... A88: UTI Value Regular Growth Plan | D88: 103098 | E88: INF789F01AG5

Sheet Sheet5
A1: MF names inth elsit | B1: #,Input Fund Name,Found Fund Name,AMFI Code,ISIN Code | C1: {=_xlfn.TEXTSPLIT(B1,",")} -> # | D1: Input Fund Name | E1: Found Fund Name | F1: AMFI Code | G1: ISIN Code | H1: AMFI Code | I1: ISIN Code
A2: Aditya Birla Sun Life Corporate Bond Regular Growth Plan | B2: 1,Aditya Birla Sun Life Corporate Bond Regular Growth Plan,ABSL Corporate Bond Fund-Regular Growth,103174,INF209K01BR9 | C2: {=_xlfn.TEXTSPLIT(B2,",")} -> 1 | D2: Aditya Birla Sun Life Corporate Bond Regular Growth Plan | E2: ABSL Corporate Bond Fund-Regular Growth | F2: 103174 | G2: INF209K01BR9 | H2: 103174 | I2: INF209K01BR9
A3: Aditya Birla Sun Life Dynamic Bond Retail Growth Plan | B3: 2,Aditya Birla Sun Life Dynamic Bond Retail Growth Plan,ABSL Dynamic Bond Fund-Regular Growth,103176,INF209K01BT5 | C3: {=_xlfn.TEXTSPLIT(B3,",")} -> 2 | D3: Aditya Birla Sun Life Dynamic Bond Retail Growth Plan | E3: ABSL Dynamic Bond Fund-Regular Growth | F3: 103176 | G3: INF209K01BT5 | H3: 103176 | I3: INF209K01BT5
A4: Aditya Birla Sun Life Floating Rate Regular Growth Plan | B4: 3,Aditya Birla Sun Life Floating Rate Regular Growth Plan,ABSL Floating Rate Fund-Regular Growth,103168,INF209K01BO6 | C4: {=_xlfn.TEXTSPLIT(B4,",")} -> 3 | D4: Aditya Birla Sun Life Floating Rate Regular Growth Plan | E4: ABSL Floating Rate Fund-Regular Growth | F4: 103168 | G4: INF209K01BO6 | H4: 103168 | I4: INF209K01BO6
A5: Aditya Birla Sun Life Large Cap Growth Plan | B5: 4,Aditya Birla Sun Life Large Cap Growth Plan,ABSL Large Cap Fund-Regular Growth,103173,INF209K01BR9 | C5: {=_xlfn.TEXTSPLIT(B5,",")} -> 4 | D5: Aditya Birla Sun Life Large Cap Growth Plan | E5: ABSL Large Cap Fund-Regular Growth | F5: 103173 | G5: INF209K01BR9 | H5: 103173 | I5: INF209K01BR9
A6: Aditya Birla Sun Life Medium Term Growth Plan | B6: 5,Aditya Birla Sun Life Medium Term Growth Plan,ABSL Medium Term Plan-Regular Growth,110372,INF209K01565 | C6: {=_xlfn.TEXTSPLIT(B6,",")} -> 5 | D6: Aditya Birla Sun Life Medium Term Growth Plan | E6: ABSL Medium Term Plan-Regular Growth | F6: 110372 | G6: INF209K01565 | H6: 110372 | I6: INF209K01565
A7: Aditya Birla Sun Life Short Term Growth Plan | B7: 6,Aditya Birla Sun Life Short Term Growth Plan,ABSL Short Term Fund-Regular Growth,103172,INF209K01BP3 | C7: {=_xlfn.TEXTSPLIT(B7,",")} -> 6 | D7: Aditya Birla Sun Life Short Term Growth Plan | E7: ABSL Short Term Fund-Regular Growth | F7: 103172 | G7: INF209K01BP3 | H7: 103172 | I7: INF209K01BP3
A8: Axis Corporate Bond Growth Direct Plan | B8: 7,Axis Corporate Bond Growth Direct Plan,Axis Corporate Bond Fund-Direct Growth,141589,INF846K01X36 | C8: {=_xlfn.TEXTSPLIT(B8,",")} -> 7 | D8: Axis Corporate Bond Growth Direct Plan | E8: Axis Corporate Bond Fund-Direct Growth | F8: 141589 | G8: INF846K01X36 | H8: 141589 | I8: INF846K01X36
A9: Axis Dynamic Bond Growth Direct Plan | B9: 8,Axis Dynamic Bond Growth Direct Plan,Axis Dynamic Bond Fund-Direct Growth,120361,INF846K01D55 | C9: {=_xlfn.TEXTSPLIT(B9,",")} -> 8 | D9: Axis Dynamic Bond Growth Direct Plan | E9: Axis Dynamic Bond Fund-Direct Growth | F9: 120361 | G9: INF846K01D55 | H9: 120361 | I9: INF846K01D55
A10: Axis Focused Growth Direct Plan | B10: 9,Axis Focused Growth Direct Plan,Axis Focused 25 Fund-Direct Growth,120377,INF846K01D22 | C10: {=_xlfn.TEXTSPLIT(B10,",")} -> 9 | D10: Axis Focused Growth Direct Plan | E10: Axis Focused 25 Fund-Direct Growth | F10: 120377 | G10: INF846K01D22 | H10: 120377 | I10: INF846K01D22
A11: Axis Focused Regular Growth Plan | B11: 10,Axis Focused Regular Growth Plan,Axis Focused 25 Fund-Regular Growth,117621,INF846K01CH7 | C11: {=_xlfn.TEXTSPLIT(B11,",")} -> 10 | D11: Axis Focused Regular Growth Plan | E11: Axis Focused 25 Fund-Regular Growth | F11: 117621 | G11: INF846K01CH7 | H11: 117621 | I11: INF846K01CH7
A12: Axis Large Cap Growth Direct Plan | B12: 11,Axis Large Cap Growth Direct Plan,Axis Large Cap Fund-Direct Growth,120353,INF846K01D48 | C12: {=_xlfn.TEXTSPLIT(B12,",")} -> 11 | D12: Axis Large Cap Growth Direct Plan | E12: Axis Large Cap Fund-Direct Growth | F12: 120353 | G12: INF846K01D48 | H12: 120353 | I12: INF846K01D48
... A91: HDFC Balanced Growth Plan | B91: 90,HDFC Balanced Growth Plan,HDFC Balanced Growth Plan- regular,100119,INF179K01830 | C91: {=_xlfn.TEXTSPLIT(B91,",")} -> 90 | D91: HDFC Balanced Growth Plan | E91: HDFC Balanced Growth Plan- regular | F91: 100119 | G91: INF179K01830 | H91: 100119 | I91: INF179K01830
